container_collection/__init__.py
container_collection/__main__.py
container_collection/batch/__init__.py
container_collection/batch/check_batch_job.py
container_collection/batch/get_batch_logs.py
container_collection/batch/make_batch_job.py
container_collection/batch/register_batch_job.py
container_collection/batch/submit_batch_job.py
container_collection/batch/terminate_batch_job.py
container_collection/docker/__init__.py
container_collection/docker/check_docker_job.py
container_collection/docker/clean_docker_job.py
container_collection/docker/create_docker_volume.py
container_collection/docker/get_docker_logs.py
container_collection/docker/make_docker_job.py
container_collection/docker/remove_docker_volume.py
container_collection/docker/run_docker_command.py
container_collection/docker/submit_docker_job.py
container_collection/docker/terminate_docker_job.py
container_collection/fargate/__init__.py
container_collection/fargate/check_fargate_task.py
container_collection/fargate/make_fargate_task.py
container_collection/fargate/register_fargate_task.py
container_collection/fargate/submit_fargate_task.py
container_collection/fargate/terminate_fargate_task.py
container_collection/manifest/__init__.py
container_collection/manifest/filter_manifest_files.py
container_collection/manifest/find_missing_conditions.py
container_collection/manifest/summarize_manifest_files.py
container_collection/manifest/update_manifest_contents.py
container_collection/py.typed
container_collection/template/__init__.py
container_collection/template/generate_input_contents.py
container_collection-1.1.0.dist-info/LICENSE
container_collection-1.1.0.dist-info/METADATA
container_collection-1.1.0.dist-info/WHEEL
container_collection-1.1.0.dist-info/RECORD
