Metadata-Version: 2.1
Name: container-collection
Version: 1.1.0
Summary: Collection of tasks for running containerized models.
License: BSD-3-Clause
Author: Jessica S. Yu
Author-email: jesyu@uw.edu
Requires-Python: >=3.9,<4.0
Classifier: License :: OSI Approved :: BSD License
Classifier: Programming Language :: Python :: 3
Classifier: Programming Language :: Python :: 3.9
Classifier: Programming Language :: Python :: 3.10
Classifier: Programming Language :: Python :: 3.11
Classifier: Programming Language :: Python :: 3.12
Requires-Dist: boto3 (>=1.24.59,<2.0.0)
Requires-Dist: deepdiff (>=5.8.1,<6.0.0)
Requires-Dist: docker (>=7.1.0,<8.0.0)
Requires-Dist: numpy (>=1.24.2,<2.0.0)
Requires-Dist: pandas (>=1.5.3,<2.0.0)
Requires-Dist: prefect (>=2.8.2,<3.0.0)
Requires-Dist: tabulate (>=0.9.0,<0.10.0)
